[
    {
        "name":"Ausanerek",
        "population":"550",
        "mine":"Ol'Boosie's Mines",
        "laborers":"425",
        "laborOutput":"4",
        "taxRate":"0.02",
        "nationalTaxRate":"0.85",
        "laborPayrate":"60",
        "miscExpenses":"0.85",
        "workdays":"300"
    },
    {
        "name":"Silverton",
        "population":"1550",
        "mine":"Trusties Mine Company",
        "laborers":"1200",
        "laborOutput":"4",
        "taxRate":"0.03",
        "nationalTaxRate":"0.45",
        "laborPayrate":"60",
        "miscExpenses":"0.85",
        "workdays":"300"
    }
]
